Metadata-Version: 2.1
Name: cghla
Version: 0.2.3
Summary: Tools for finding HLA alleles for WGS/RNAseq samples
Home-page: http://github.com/compgen-io/cghla/
Author: Marcus Breese
Author-email: marcus@breese.com
Requires-Python: >=3.9
License-File: LICENSE
